SHDB/__init__.py
SHDL/__init__.py
SHDL/errors.py
SHDL/py.typed
SHDL/source_map.py
SHDL/compiler/__init__.py
SHDL/compiler/analyzer.py
SHDL/compiler/ast.py
SHDL/compiler/cli.py
SHDL/compiler/codegen.py
SHDL/compiler/compiler.py
SHDL/compiler/debug_codegen.py
SHDL/compiler/debug_info_gen.py
SHDL/compiler/lexer.py
SHDL/compiler/parser.py
SHDL/debugger/__init__.py
SHDL/debugger/circuit.py
SHDL/debugger/cli.py
SHDL/debugger/controller.py
SHDL/debugger/debuginfo.py
SHDL/debugger/sourcemap.py
SHDL/debugger/symbols.py
SHDL/driver/__init__.py
SHDL/driver/circuit.py
SHDL/driver/exceptions.py
SHDL/flattener/__init__.py
SHDL/flattener/ast.py
SHDL/flattener/flattener.py
SHDL/flattener/lexer.py
SHDL/flattener/parser.py
SHDL/flattener/tokens.py
SHDL/semantic/__init__.py
SHDL/semantic/analyzer.py
SHDL/semantic/connection.py
SHDL/semantic/resolver.py
SHDL/semantic/type_check.py
SHDL/semantic/warnings.py
pyshdl-0.2.3.dist-info/METADATA
pyshdl-0.2.3.dist-info/WHEEL
pyshdl-0.2.3.dist-info/entry_points.txt
pyshdl-0.2.3.dist-info/licenses/LICENSE
pyshdl-0.2.3.dist-info/RECORD
