Metadata-Version: 2.4
Name: PySHDL
Version: 0.2.3
Summary: SHDL (Simple Hardware Description Language) is a minimal HDL designed for creating digital circuits and easily simulating them. It compiles directly to C for maximum performance and portability. PySHDL is the Python interface for SHDL.
Project-URL: Homepage, https://github.com/rafa-rrayes/SHDL
Project-URL: Repository, https://github.com/rafa-rrayes/SHDL
Project-URL: Documentation, https://rafa-rrayes.github.io/SHDL/
Author-email: rafa-rrayes <rafa@rayes.com.br>
License-File: LICENSE
Requires-Python: >=3.10
Provides-Extra: dev
Requires-Dist: mypy>=1.8.0; extra == 'dev'
Requires-Dist: pytest-cov>=5.0.0; extra == 'dev'
Requires-Dist: pytest>=8.0.0; extra == 'dev'
Requires-Dist: ruff>=0.7.0; extra == 'dev'
